{
  "schema_version": 1,
  "slug": "x-twitter",
  "cli_name": "x-twitter-pp-cli",
  "version": "2026.6.10",
  "released_at": "2026-06-18T03:04:04Z",
  "source_commit": "bb795739ffc12c4f7cfcaa2b00eca6b0d39b3653",
  "printing_press_version": "4.20.1",
  "run_id": "20260603-230951",
  "changes": [
    {
      "title": "fix(x-twitter): refresh oauth2 user-context tokens",
      "pr": 1273,
      "url": "https://github.com/mvanhorn/printing-press-library/pull/1273",
      "commit": "bb795739ffc12c4f7cfcaa2b00eca6b0d39b3653"
    }
  ]
}
